topsis_iyasha_102103034/__init__.py
topsis_iyasha_102103034/topsis.py
topsis_iyasha_102103034-0.1.dist-info/LICENSE.txt
topsis_iyasha_102103034-0.1.dist-info/METADATA
topsis_iyasha_102103034-0.1.dist-info/WHEEL
topsis_iyasha_102103034-0.1.dist-info/entry_points.txt
topsis_iyasha_102103034-0.1.dist-info/top_level.txt
topsis_iyasha_102103034-0.1.dist-info/RECORD
