Metadata-Version: 2.1
Name: topsis_iyasha_102103034
Version: 0.1
Summary: Topsis Package
Author: iyasha
Author-email: iiyasha_be21@thapar.edu
License: MIT
Keywords: TOPSIS,MCDM
Classifier: Development Status :: 3 - Alpha
Classifier: Intended Audience :: Developers
Classifier: Topic :: Software Development :: Build Tools
Classifier: License :: OSI Approved :: MIT License
Classifier: Programming Language :: Python :: 3
License-File: LICENSE.txt
Requires-Dist: numpy
Requires-Dist: pandas
